{
    "magic_types" : 
    [
        {   "unique_id" : "MAGICIAN",
            "translations" : 
            { 
                "en" : "Magician",
                "de" : "Zauberer"
            },
            "types" : [ "magic" ],
            "priorities" : 
            {
                "0" : 
                {
                    "starting_magic" : "6",
                    "free_spells"    : "10",
                    "free_skills"    : ["2", "5"]
                },
                "1" :
                {
                    "starting_magic" : "4",
                    "free_spells"    : "7",
                    "free_skills"    : ["2", "4"]
                },
                "2" :
                {
                    "starting_magic" : "3",
                    "free_spells"    : "5"
                }
            }
        },
        {   "unique_id" : "ASPECT_MAGICIAN",
            "translations" : 
            { 
                "en" : "Aspected Magician",
                "de" : "Aspektzauberer"
            },
            "types" : [ "magic", "aspected" ],
            "priorities" : 
            {
                "1" :
                {
                    "starting_magic"         : "5",
                    "free_spells"            : "0",
                    "free_skill_groups"    : ["1", "4"]
                },
                "2" :
                {
                    "starting_magic"         : "3",
                    "free_spells"            : "0",
                    "free_skill_groups"    : ["1", "2"]
                },
                "3" :
                {
                    "starting_magic"         : "2",
                    "free_spells"            : "0"
                }
            }
        },
        {   "unique_id" : "MYSTIC_ADEPT",
            "translations" : 
            { 
                "en" : "Mystic Adept",
                "de" : "Magieradept"
            },
            "types" : [ "magic", "adept" ],
            "priorities" : 
            {
                "0" : 
                {
                    "starting_magic"     : "6",
                    "free_spells"        : "10",
                    "free_power_points"  : "0",
                    "free_skills"        : ["2", "5"]
                },
                "1" :
                {
                    "starting_magic"     : "4",
                    "free_spells"        : "7",
                    "free_power_points"  : "0",
                    "free_skills"        : ["2", "4"]
                },
                "2" :
                {
                    "starting_magic"     : "3",
                    "free_spells"        : "5",
                    "free_power_points"  : "0"
                }
            }
        },
        {   "unique_id" : "ADEPT",
            "translations" : 
            { 
                "en" : "Adept",
                "de" : "Adept"
            },
            "types" : [ "adept" ],
            "priorities" : 
            {
                "1" :
                {
                    "starting_magic"     : "6",
                    "free_skills"        : ["1", "4"]
                },
                "2" :
                {
                    "starting_magic"     : "4",
                    "free_power_points"  : "4",
                    "free_skills"        : ["1", "2"]
                },
                "3" :
                {
                    "starting_magic"     : "2",
                    "free_power_points"  : "2"
                }
            }
        },
        {   "unique_id" : "TECHNOMANCER",
            "translations" : 
            { 
                "en" : "Technomancer",
                "de" : "Technomancer"
            },
            "types" : [ "resonance" ],
            "priorities" : 
            {
                "0" : 
                {
                    "starting_magic" : "6",
                    "free_spells"    : "5",
                    "free_skills"    : ["2", "5"]
                },
                "1" :
                {
                    "starting_magic" : "4",
                    "free_spells"    : "2",
                    "free_skills"    : ["2", "4"]
                },
                "2" :
                {
                    "starting_magic" : "3",
                    "free_spells"    : "1"
                }
            }
        }
    ],
    "spell_categories" : [
      { "unique_id" : "COMBAT",
        "translations" : 
        { 
            "en" : "Combat Spells",
            "de" : "Kampfzauber"
        }
      },
      { "unique_id" : "DETECTION",
        "translations" : 
        { 
            "en" : "Detection Spells",
            "de" : "Wahrnehmungszauber"
        }
      },
      { "unique_id" : "HEALTH",
        "translations" : 
        { 
            "en" : "Health Spells",
            "de" : "Heilzauber"
        }
      },
      { "unique_id" : "ILLUSION",
        "translations" : 
        { 
            "en" : "Illusion Spells",
            "de" : "Illusionszauber"
        }
      },
      { "unique_id" : "MANIPULATION",
        "translations" : 
        { 
            "en" : "Manipulation Spells",
            "de" : "Manipulationszauber"
        }
      }
    ],
    "spells" : [
      { "unique_id"     : "ACID_STREAM",
        "translations" : 
        { 
            "en" : "Acid Stream",
            "de" : "Säurestrahl"
        },
        "category"    : "COMBAT",
        "type"        : "P",
        "range"       : "LOS",
        "damage"      : "P",
        "duration"    : "I",
        "drain"       : "F - 3",
        "descriptors" : [ "indirect", "elemental" ]
      },
      { "unique_id"     : "TOXIC_WAVE",
        "translations" : 
        { 
            "en" : "Toxic Wave",
            "de" : "Säurewelle"
        },
        "category"    : "COMBAT",
        "type"        : "P",
        "range"       : "LOS(A)",
        "damage"      : "P",
        "duration"    : "I",
        "drain"       : "F - 1",
        "descriptors" : [ "indirect", "elemental" ]
      },
      { "unique_id"     : "PUNCH",
        "translations" : 
        { 
            "en" : "Punch",
            "de" : "Schlag"
        },
        "category"    : "COMBAT",
        "type"        : "P",
        "range"       : "T",
        "damage"      : "S",
        "duration"    : "I",
        "drain"       : "F - 6",
        "descriptors" : [ "indirect" ]
      },
      { "unique_id"     : "CLOUT",
        "translations" : 
        { 
            "en" : "Clout",
            "de" : "Stoss"
        },
        "category"    : "COMBAT",
        "type"        : "P",
        "range"       : "LOS",
        "damage"      : "S",
        "duration"    : "I",
        "drain"       : "F - 3",
        "descriptors" : [ "indirect" ]
      },
      { "unique_id"     : "BLAST",
        "translations" : 
        { 
            "en" : "Blast",
            "de" : "Druckwelle"
        },
        "category"    : "COMBAT",
        "type"        : "P",
        "range"       : "LOS(A)",
        "damage"      : "S",
        "duration"    : "I",
        "drain"       : "F",
        "descriptors" : [ "indirect" ]
      },
      { "unique_id"     : "DEATH_TOUCH",
        "translations" : 
        { 
            "en" : "Death Touch",
            "de" : "Todeshand"
        },
        "category"    : "COMBAT",
        "type"        : "M",
        "range"       : "T",
        "damage"      : "P",
        "duration"    : "I",
        "drain"       : "F - 6",
        "descriptors" : [ "direct" ]
      },
      { "unique_id"     : "MANABOLT",
        "translations" : 
        { 
            "en" : "Manabolt",
            "de" : "Manablitz"
        },
        "category"    : "COMBAT",
        "type"        : "M",
        "range"       : "LOS",
        "damage"      : "P",
        "duration"    : "I",
        "drain"       : "F - 3",
        "descriptors" : [ "direct" ]
      },
      { "unique_id"     : "MANABALL",
        "translations" : 
        { 
            "en" : "Manaball",
            "de" : "Manaball"
        },
        "category"    : "COMBAT",
        "type"        : "M",
        "range"       : "LOS(A)",
        "damage"      : "P",
        "duration"    : "I",
        "drain"       : "F",
        "descriptors" : [ "direct" ]
      },
      { "unique_id"     : "FLAMETHROWER",
        "translations" : 
        { 
            "en" : "Flamethrower",
            "de" : "Flammenwerfer"
        },
        "category"    : "COMBAT",
        "type"        : "P",
        "range"       : "LOS",
        "damage"      : "P",
        "duration"    : "I",
        "drain"       : "F - 3",
        "descriptors" : [ "indirect", "elemental" ]
      },
      { "unique_id"    : "FIREBALL",
        "translations" : 
        { 
            "en" : "Fireball",
            "de" : "Feuerball"
        },
        "category"    : "COMBAT",
        "type"        : "P",
        "range"       : "LOS(A)",
        "damage"      : "P",
        "duration"    : "I",
        "drain"       : "F - 1",
        "descriptors" : [ "indirect", "elemental" ]
      },
      { "unique_id"    : "LIGHTNING_BOLT",
        "translations" : 
        { 
            "en" : "Lightning Bolt",
            "de" : "Blitzstrahl"
        },
        "category"    : "COMBAT",
        "type"        : "P",
        "range"       : "LOS",
        "damage"      : "P",
        "duration"    : "I",
        "drain"       : "F - 3",
        "descriptors" : [ "indirect", "elemental" ]
      },
      { "unique_id"    : "BALL_LIGHTNING",
        "translations" : 
        { 
            "en" : "Ball Lightning",
            "de" : "Kugelblitz"
        },
        "category"    : "COMBAT",
        "type"        : "P",
        "range"       : "LOS(A)",
        "damage"      : "P",
        "duration"    : "I",
        "drain"       : "F - 1",
        "descriptors" : [ "indirect", "elemental" ]
      },
      { "unique_id"    : "SHATTER",
        "translations" : 
        { 
            "en" : "Shatter",
            "de" : "Energieschlag"
        },
        "category"    : "COMBAT",
        "type"        : "P",
        "range"       : "T",
        "damage"      : "P",
        "duration"    : "I",
        "drain"       : "F - 6",
        "descriptors" : [ "direct" ]
      },
      { "unique_id"    : "POWERBOLT",
        "translations" : 
        { 
            "en" : "Powerbolt",
            "de" : "Energieblitz"
        },
        "category"    : "COMBAT",
        "type"        : "P",
        "range"       : "LOS",
        "damage"      : "P",
        "duration"    : "I",
        "drain"       : "F - 3",
        "descriptors" : [ "direct" ]
      },
      { "unique_id"    : "POWERBALL",
        "translations" : 
        { 
            "en" : "Powerball",
            "de" : "Energieball"
        },
        "category"    : "COMBAT",
        "type"        : "P",
        "range"       : "LOS(A)",
        "damage"      : "P",
        "duration"    : "I",
        "drain"       : "F",
        "descriptors" : [ "direct" ]
      },
      { "unique_id"    : "KNOCKOUT",
        "translations" : 
        { 
            "en" : "Knockout",
            "de" : "Schockhand"
        },
        "category"    : "COMBAT",
        "type"        : "M",
        "range"       : "T",
        "damage"      : "S",
        "duration"    : "I",
        "drain"       : "F - 6",
        "descriptors" : [ "direct" ]
      },
      { "unique_id"    : "STUNBOLT",
        "translations" : 
        { 
            "en" : "Stunbolt",
            "de" : "Betäubungsblitz"
        },
        "category"    : "COMBAT",
        "type"        : "M",
        "range"       : "LOS",
        "damage"      : "S",
        "duration"    : "I",
        "drain"       : "F - 3",
        "descriptors" : [ "direct" ]
      },
      { "unique_id"    : "STUNBALL",
        "translations" : 
        { 
            "en" : "Stunball",
            "de" : "Betäubungsball"
        },
        "category"    : "COMBAT",
        "type"        : "M",
        "range"       : "LOS(A)",
        "damage"      : "S",
        "duration"    : "I",
        "drain"       : "F",
        "descriptors" : [ "direct" ]
      },
      { "unique_id"    : "ANALYZE_DEVICE",
        "translations" : 
        { 
            "en" : "Analyze Device",
            "de" : "Gerät Analysieren"
        },
        "category"        : "DETECTION",
        "type"            : "P",
        "range"           : "T",
        "duration"        : "S",
        "drain"           : "F - 3",
        "descriptors"     : [ "active", "directional" ]
      },
      { "unique_id"    : "ANALYZE_MAGIC",
        "translations" : 
        { 
            "en" : "Analyze Magic",
            "de" : "Magie Analysieren"
        },
        "category"        : "DETECTION",
        "type"            : "P",
        "range"           : "T",
        "duration"        : "S",
        "drain"           : "F - 3",
        "descriptors"     : [ "active", "directional" ]
      },
      { "unique_id"    : "ANALYZE_TRUTH",
        "translations" : 
        { 
            "en" : "Analyze Truth",
            "de" : "Wahrheit Prüfen"
        },
        "category"        : "DETECTION",
        "type"            : "P",
        "range"           : "T",
        "duration"        : "S",
        "drain"           : "F - 2",
        "descriptors"     : [ "active", "directional" ]
      },
      { "unique_id"    : "CLAIRAUDIENCE",
        "translations" : 
        { 
            "en" : "Clairaudience",
            "de" : "Hellhören"
        },
        "category"        : "DETECTION",
        "type"            : "M",
        "range"           : "T",
        "duration"        : "S",
        "drain"           : "F - 3",
        "descriptors"     : [ "passive", "directional" ]
      },
      { "unique_id"    : "CLAIRVOYANCE",
        "translations" : 
        { 
            "en" : "Clairvoyance",
            "de" : "Hellsicht"
        },
        "category"        : "DETECTION",
        "type"            : "M",
        "range"           : "T",
        "duration"        : "S",
        "drain"           : "F - 3",
        "descriptors"     : [ "passive", "directional" ]
      },
      { "unique_id"    : "COMBAT_SENSE",
        "translations" : 
        { 
            "en" : "Combat Sense",
            "de" : "Kampfsinn"
        },
        "category"        : "DETECTION",
        "type"            : "M",
        "range"           : "T",
        "duration"        : "S",
        "drain"           : "F",
        "descriptors"     : [ "active", "psychic" ]
      },
      { "unique_id"    : "DETECT_ENEMIES",
        "translations" : 
        { 
            "en" : "Detect Enemies",
            "de" : "Feinde Entdecken"
        },
        "category"        : "DETECTION",
        "type"            : "M",
        "range"           : "T",
        "duration"        : "S",
        "drain"           : "F - 2",
        "descriptors"     : [ "active", "area" ]
      },
      { "unique_id"    : "DETECT_ENEMIES_EXTENDED",
        "translations" : 
        { 
            "en" : "Detect Enemies (Extended)",
            "de" : "Erweitertes Feinde Entdecken"
        },
        "category"        : "DETECTION",
        "type"            : "M",
        "range"           : "T",
        "duration"        : "S",
        "drain"           : "F",
        "descriptors"     : [ "active", "extended area" ]
      },
      { "unique_id"    : "DETECT_INDIVIDUAL",
        "translations" : 
        { 
            "en" : "Detect Individual",
            "de" : "Individuum Entdecken"
        },
        "category"        : "DETECTION",
        "type"            : "M",
        "range"           : "T",
        "duration"        : "S",
        "drain"           : "F - 3",
        "descriptors"     : [ "active", "area" ]
      },
      { "unique_id"    : "DETECT_LIFE",
        "translations" : 
        { 
            "en" : "Detect Life",
            "de" : "Leben Entdecken"
        },
        "category"        : "DETECTION",
        "type"            : "M",
        "range"           : "T",
        "duration"        : "S",
        "drain"           : "F - 3",
        "descriptors"     : [ "active", "area" ]
      },
      { "unique_id"    : "DETECT_LIFE_EXTENDED",
        "translations" : 
        { 
            "en" : "Detect Life (Extended)",
            "de" : "Erweitertes Leben Entdecken"
        },
        "category"        : "DETECTION",
        "type"            : "M",
        "range"           : "T",
        "duration"        : "S",
        "drain"           : "F - 1",
        "descriptors"     : [ "active", "extended area" ]
      },
      { "unique_id"    : "DETECT_LIFE_FORM",
        "translations" : 
        { 
            "en" : "Detect [Life Form]",
            "de" : "[Lebensform] Entdecken"
        },
        "category"        : "DETECTION",
        "type"            : "M",
        "range"           : "T",
        "duration"        : "S",
        "drain"           : "F - 2",
        "requires_custom" : "true",  
        "descriptors"     : [ "active", "area" ]
      },
      { "unique_id"    : "DETECT_LIFE_FORM_EXTENDED",
        "translations" : 
        { 
            "en" : "Detect [Life Form] (Extended)",
            "de" : "Erweitertes [Lebensform] Entdecken"
        },
        "category"        : "DETECTION",
        "type"            : "M",
        "range"           : "T",
        "duration"        : "S",
        "drain"           : "F",
        "requires_custom" : "true",  
        "descriptors"     : [ "active", "extended area" ]
      },
      { "unique_id"     : "DETECT_MAGIC",
        "translations" : 
        { 
            "en" : "Detect Magic",
            "de" : "Magie Entdecken"
        },
        "category"        : "DETECTION",
        "type"            : "M",
        "range"           : "T",
        "duration"        : "S",
        "drain"           : "F - 2",
        "descriptors"     : [ "active", "area" ]
      },
      { "unique_id"    : "DETECT_MAGIC_EXTENDED",
        "translations" : 
        { 
            "en" : "Detect Magic (Extended)",
            "de" : "Erweitertes Magie Entdecken"
        },
        "category"        : "DETECTION",
        "type"            : "M",
        "range"           : "T",
        "duration"        : "S",
        "drain"           : "F",
        "descriptors"     : [ "active", "extended area" ]
      },
      { "unique_id"    : "DETECT_OBJECT",
        "translations" : 
        { 
            "en" : "Detect [Object]",
            "de" : "[Objekt] Entdecken"
        },
        "category"        : "DETECTION",
        "type"            : "M",
        "range"           : "T",
        "duration"        : "S",
        "drain"           : "F - 2",
        "requires_custom" : "true",  
        "descriptors"     : [ "active", "area" ]
      },
      { "unique_id"    : "MINDLINK",
        "translations" : 
        { 
            "en" : "Mindlink",
            "de" : "Telepathie"
        },
        "category"        : "DETECTION",
        "type"            : "M",
        "range"           : "T",
        "duration"        : "S",
        "drain"           : "F - 1",
        "descriptors"     : [ "active", "psychic" ]
      },
      { "unique_id"    : "MIND_PROBE",
        "translations" : 
        { 
            "en" : "Mind Probe",
            "de" : "Geistessonde"
        },
        "category"        : "DETECTION",
        "type"            : "M",
        "range"           : "T",
        "duration"        : "S",
        "drain"           : "F",
        "descriptors"     : [ "active", "directional" ]
      },
      { "unique_id"    : "ANTIDOTE",
        "translations" : 
        { 
            "en" : "Antidote",
            "de" : "Gegenmittel"
        },
        "category"        : "HEALTH",
        "type"            : "M",
        "range"           : "T",
        "duration"        : "P",
        "drain"           : "F - 4",
        "essence_effect"  : "true"
      },
      { "unique_id"    : "CURE_SICKNESS",
        "translations" : 
        { 
            "en" : "Cure Sickness",
            "de" : "Krankheit Heilen"
        },
        "category"        : "HEALTH",
        "type"            : "M",
        "range"           : "T",
        "duration"        : "P",
        "drain"           : "F - 4",
        "essence_effect"  : "true"
      },
      { "unique_id"    : "DECREASE_ATTRIBUTE",
        "translations" : 
        { 
            "en" : "Decrease [Attribute]",
            "de" : "[Attribut] Senken"
        },
        "category"        : "HEALTH",
        "type"            : "P",
        "range"           : "T",
        "duration"        : "S",
        "drain"           : "F - 2",
        "essence_effect"  : "true",
        "requires_custom" : "true"
      },
      { "unique_id"    : "DETOX",
        "translations" : 
        { 
            "en" : "Detox",
            "de" : "Entgiftung"
        },
        "category"        : "HEALTH",
        "type"            : "M",
        "range"           : "T",
        "duration"        : "P",
        "drain"           : "F - 6",
        "essence_effect"  : "false"
      },
      { "unique_id"    : "HEAL",
        "translations" : 
        { 
            "en" : "Heal",
            "de" : "Heilen"
        },
        "category"        : "HEALTH",
        "type"            : "M",
        "range"           : "T",
        "duration"        : "P",
        "drain"           : "F - 4",
        "essence_effect"  : "true"
      },
      { "unique_id"    : "INCREASE_ATTRIBUTE",
        "translations" : 
        { 
            "en" : "Increase [Attribute]",
            "de" : "[Attribut] Steigern"
        },
        "category"        : "HEALTH",
        "type"            : "P",
        "range"           : "T",
        "duration"        : "S",
        "drain"           : "F - 3",
        "essence_effect"  : "true",
        "requires_custom" : "true"
      },
      { "unique_id"    : "INCREASE_REFLEXES",
        "translations" : 
        { 
            "en" : "Increase Reflexes",
            "de" : "Reflexe Steigern"
        },
        "category"        : "HEALTH",
        "type"            : "P",
        "range"           : "T",
        "duration"        : "S",
        "drain"           : "F",
        "essence_effect"  : "true"
      },
      { "unique_id"    : "OXYGENATE",
        "translations" : 
        { 
            "en" : "Oxygenate",
            "de" : "Sauerstoffmaske"
        },
        "category"        : "HEALTH",
        "type"            : "P",
        "range"           : "T",
        "duration"        : "S",
        "drain"           : "F - 5",
        "essence_effect"  : "false"
      },
      { "unique_id"    : "PROPHYLAXIS",
        "translations" : 
        { 
            "en" : "Prophylaxis",
            "de" : "Prophylaxe"
        },
        "category"        : "HEALTH",
        "type"            : "M",
        "range"           : "T",
        "duration"        : "S",
        "drain"           : "F - 4",
        "essence_effect"  : "false"
      },
      { "unique_id"    : "RESIST_PAIN",
        "translations" : 
        { 
            "en" : "Resist Pain",
            "de" : "Schmerzresistenz"
        },
        "category"        : "HEALTH",
        "type"            : "M",
        "range"           : "T",
        "duration"        : "P",
        "drain"           : "(Damage Value) - 5",
        "essence_effect"  : "false"
      },
      { "unique_id"    : "STABILIZE",
        "translations" : 
        { 
            "en" : "Stabilize",
            "de" : "Stabilisieren"
        },
        "category"        : "HEALTH",
        "type"            : "M",
        "range"           : "T",
        "duration"        : "P",
        "drain"           : "F - 4",
        "essence_effect"  : "false"
      },
      { "unique_id"     : "AGONY",
        "translations" : 
        { 
            "en" : "Agony",
            "de" : "Schmerz"
        },
        "category"        : "ILLUSION",
        "type"            : "M",
        "range"           : "LOS",
        "duration"        : "S",
        "drain"           : "F - 4",
        "descriptors"     : [ "realistic", "single-sense" ]
      },
      { "unique_id"     : "MASS_AGONY",
        "translations" : 
        { 
            "en" : "Mass Agony",
            "de" : "Massenschmerz"
        },
        "category"        : "ILLUSION",
        "type"            : "M",
        "range"           : "LOS(A)",
        "duration"        : "S",
        "drain"           : "F - 2",
        "descriptors"     : [ "realistic", "single-sense", "area" ]
      },
      { "unique_id"    : "BUGS",
        "translations" : 
        { 
            "en" : "Bugs",
            "de" : "Viecher"
        },
        "category"        : "ILLUSION",
        "type"            : "M",
        "range"           : "LOS",
        "duration"        : "S",
        "drain"           : "F - 3",
        "descriptors"     : [ "realistic", "multi-sense" ]
      },
      { "unique_id"     : "SWARM",
        "translations" : 
        { 
            "en" : "Swarm",
            "de" : "Schwarm"
        },
        "category"        : "ILLUSION",
        "type"            : "M",
        "range"           : "LOS(A)",
        "duration"        : "S",
        "drain"           : "F - 1",
        "descriptors"     : [ "realistic", "multi-sense", "area" ]
      },
      { "unique_id"    : "CONFUSION",
        "translations" : 
        { 
            "en" : "Confusion",
            "de" : "Verwirrung"
        },
        "category"        : "ILLUSION",
        "type"            : "M",
        "range"           : "LOS",
        "duration"        : "S",
        "drain"           : "F - 3",
        "descriptors"     : [ "realistic", "multi-sense" ]
      },
      { "unique_id"    : "MASS_CONFUSION",
        "translations" : 
        { 
            "en" : "Mass Confusion",
            "de" : "Massenverwirrung"
        },
        "category"        : "ILLUSION",
        "type"            : "M",
        "range"           : "LOS(A)",
        "duration"        : "S",
        "drain"           : "F - 1",
        "descriptors"     : [ "realistic", "multi-sense", "area" ]
      },
      { "unique_id"    : "CHAOS",
        "translations" : 
        { 
            "en" : "Chaos",
            "de" : "Chaos"
        },
        "category"        : "ILLUSION",
        "type"            : "P",
        "range"           : "LOS",
        "duration"        : "S",
        "drain"           : "F - 2",
        "descriptors"     : [ "realistic", "multi-sense" ]
      },
      { "unique_id"    : "CHAOTIC_WORLD",
        "translations" : 
        { 
            "en" : "Chaotic Worls",
            "de" : "Chaotische Welt"
        },
        "category"        : "ILLUSION",
        "type"            : "P",
        "range"           : "LOS(A)",
        "duration"        : "S",
        "drain"           : "F",
        "descriptors"     : [ "realistic", "multi-sense", "area" ]
      },
      { "unique_id"    : "ENTERTAINMENT",
        "translations" : 
        { 
            "en" : "Entertainment",
            "de" : "Unterhaltung"
        },
        "category"        : "ILLUSION",
        "type"            : "M",
        "range"           : "LOS(A)",
        "duration"        : "S",
        "drain"           : "F - 3",
        "descriptors"     : [ "obvious", "multi-sense", "area" ]
      },
      { "unique_id"    : "TRID ENTERTAINMENT",
        "translations" : 
        { 
            "en" : "Trid Entertainment",
            "de" : "Trideo-Unterhaltung"
        },
        "category"        : "ILLUSION",
        "type"            : "P",
        "range"           : "LOS(A)",
        "duration"        : "S",
        "drain"           : "F - 2",
        "descriptors"     : [ "obvious", "multi-sense", "area" ]
      },
      { "unique_id"    : "INVISIBILITY",
        "translations" : 
        { 
            "en" : "Invisibility",
            "de" : "Unsichtbarkeit"
        },
        "category"        : "ILLUSION",
        "type"            : "M",
        "range"           : "LOS",
        "duration"        : "S",
        "drain"           : "F - 2",
        "descriptors"     : [ "realistic", "single-sense" ]
      },
      { "unique_id"    : "IMPROVED_INVISIBILITY",
        "translations" : 
        { 
            "en" : "Improved Invisibility",
            "de" : "Verbesserte Unsichtbarkeit"
        },
        "category"        : "ILLUSION",
        "type"            : "P",
        "range"           : "LOS",
        "duration"        : "S",
        "drain"           : "F - 1",
        "descriptors"     : [ "realistic", "single-sense" ]
      },
      { "unique_id"    : "MASK",
        "translations" : 
        { 
            "en" : "Mask",
            "de" : "Maske"
        },
        "category"        : "ILLUSION",
        "type"            : "M",
        "range"           : "T",
        "duration"        : "S",
        "drain"           : "F - 2",
        "descriptors"     : [ "realistic", "multi-sense" ]
      },
      { "unique_id"    : "PHYSICAL_MASK",
        "translations" : 
        { 
            "en" : "Physical Mask",
            "de" : "Physische Maske"
        },
        "category"        : "ILLUSION",
        "type"            : "P",
        "range"           : "T",
        "duration"        : "S",
        "drain"           : "F - 1",
        "descriptors"     : [ "realistic", "multi-sense" ]
      },
      { "unique_id"    : "PHANTASM",
        "translations" : 
        { 
            "en" : "Phantasm",
            "de" : "Trugbild"
        },
        "category"        : "ILLUSION",
        "type"            : "M",
        "range"           : "LOS(A)",
        "duration"        : "S",
        "drain"           : "F - 1",
        "descriptors"     : [ "realistic", "multi-sense", "area" ]
      },
      { "unique_id"    : "TRID_PHANTASM",
        "translations" : 
        { 
            "en" : "Trid Phantasm",
            "de" : "Trideo-Trugbild"
        },
        "category"        : "ILLUSION",
        "type"            : "P",
        "range"           : "LOS(A)",
        "duration"        : "S",
        "drain"           : "F",
        "descriptors"     : [ "realistic", "multi-sense", "area" ]
      },
      { "unique_id"    : "HUSH",
        "translations" : 
        { 
            "en" : "Hush",
            "de" : "Schweigen"
        },
        "category"        : "ILLUSION",
        "type"            : "M",
        "range"           : "LOS(A)",
        "duration"        : "S",
        "drain"           : "F - 2",
        "descriptors"     : [ "realistic", "single-sense", "area" ]
      },
      { "unique_id"    : "SILENCE",
        "translations" : 
        { 
            "en" : "Silence",
            "de" : "Stille"
        },
        "category"        : "ILLUSION",
        "type"            : "P",
        "range"           : "LOS(A)",
        "duration"        : "S",
        "drain"           : "F - 1",
        "descriptors"     : [ "realistic", "single-sense", "area" ]
      },
      { "unique_id"    : "STEALTH",
        "translations" : 
        { 
            "en" : "Stealth",
            "de" : "Leiser Schritt"
        },
        "category"        : "ILLUSION",
        "type"            : "P",
        "range"           : "LOS",
        "duration"        : "S",
        "drain"           : "F - 2",
        "descriptors"     : [ "realistic", "single-sense", "area" ]
      },
      { "unique_id"    : "ANIMATE",
        "translations" : 
        { 
            "en" : "Animate",
            "de" : "Animate"
        },
        "category"        : "MANIPULATION",
        "type"            : "P",
        "range"           : "LOS",
        "duration"        : "S",
        "drain"           : "F - 1",
        "descriptors"     : [ "physical" ]
      },
      { "unique_id"    : "MASS_ANIMATE",
        "translations" : 
        { 
            "en" : "Mass Animate",
            "de" : "Massenbelebung"
        },
        "category"        : "MANIPULATION",
        "type"            : "P",
        "range"           : "LOS(A)",
        "duration"        : "S",
        "drain"           : "F + 1",
        "descriptors"     : [ "physical", "area" ]
      },
      { "unique_id"    : "ARMOR",
        "translations" : 
        { 
            "en" : "Armor",
            "de" : "Panzerung"
        },
        "category"        : "MANIPULATION",
        "type"            : "P",
        "range"           : "LOS",
        "duration"        : "S",
        "drain"           : "F - 2",
        "descriptors"     : [ "physical" ]
      },
      { "unique_id"    : "CONTROL_ACTIONS",
        "translations" : 
        { 
            "en" : "Control Actions",
            "de" : "Handlung Beherrschen"
        },
        "category"        : "MANIPULATION",
        "type"            : "M",
        "range"           : "LOS",
        "duration"        : "S",
        "drain"           : "F - 1",
        "descriptors"     : [ "mental" ]
      },
      { "unique_id"    : "MOB_CONTROL",
        "translations" : 
        { 
            "en" : "Mob Control",
            "de" : "Mob-Kontrolle"
        },
        "category"        : "MANIPULATION",
        "type"            : "M",
        "range"           : "LOS(A)",
        "duration"        : "S",
        "drain"           : "F + 1",
        "descriptors"     : [ "mental", "area" ]
      },
      { "unique_id"     : "CONTROL_THOUGHTS",
        "translations" : 
        { 
            "en" : "Control Thoughts",
            "de" : "Gedanken Beherrschen"
        },
        "category"        : "MANIPULATION",
        "type"            : "M",
        "range"           : "LOS",
        "duration"        : "S",
        "drain"           : "F - 1",
        "descriptors"     : [ "mental" ]
      },
      { "unique_id"     : "MOB_MIND",
        "translations" : 
        { 
            "en" : "Mob Mind",
            "de" : "Mob-Bewusstsein"
        },
        "category"        : "MANIPULATION",
        "type"            : "M",
        "range"           : "LOS(A)",
        "duration"        : "S",
        "drain"           : "F + 1",
        "descriptors"     : [ "mental", "area" ]
      },
      { "unique_id"     : "FLING",
        "translations" : 
        { 
            "en" : "Fling",
            "de" : "Schleuder"
        },
        "category"        : "MANIPULATION",
        "type"            : "P",
        "range"           : "LOS",
        "duration"        : "I",
        "drain"           : "F - 2",
        "descriptors"     : [ "physical", "damaging" ]
      },
      { "unique_id"     : "ICE_SHEET",
        "translations" : 
        { 
            "en" : "Ice Sheet",
            "de" : "Eisdecke"
        },
        "category"        : "MANIPULATION",
        "type"            : "P",
        "range"           : "LOS(A)",
        "duration"        : "I",
        "drain"           : "F",
        "descriptors"     : [ "environemntal", "area" ]
      },
      { "unique_id"     : "IGNITE",
        "translations" : 
        { 
            "en" : "Ignite",
            "de" : "Entzünden"
        },
        "category"        : "MANIPULATION",
        "type"            : "P",
        "range"           : "LOS",
        "duration"        : "P",
        "drain"           : "F - 1",
        "descriptors"     : [ "physical" ]
      },
      { "unique_id"     : "INFLUENCE",
        "translations" : 
        { 
            "en" : "Influence",
            "de" : "Beeinflussen"
        },
        "category"        : "MANIPULATION",
        "type"            : "M",
        "range"           : "LOS",
        "duration"        : "P",
        "drain"           : "F - 1",
        "descriptors"     : [ "mental" ]
      },
      { "unique_id"     : "LEVITATE",
        "translations" : 
        { 
            "en" : "Levitate",
            "de" : "Levitieren"
        },
        "category"        : "MANIPULATION",
        "type"            : "P",
        "range"           : "LOS",
        "duration"        : "S",
        "drain"           : "F - 2",
        "descriptors"     : [ "physical" ]
      },
      { "unique_id"     : "LIGHT",
        "translations" : 
        { 
            "en" : "Light",
            "de" : "Licht"
        },
        "category"        : "MANIPULATION",
        "type"            : "P",
        "range"           : "LOS(A)",
        "duration"        : "S",
        "drain"           : "F - 4",
        "descriptors"     : [ "environmental", "area" ]
      },
      { "unique_id"     : "MAGIC_FINGERS",
        "translations" : 
        { 
            "en" : "Magic Fingers",
            "de" : "Zauberfinger"
        },
        "category"        : "MANIPULATION",
        "type"            : "P",
        "range"           : "LOS",
        "duration"        : "S",
        "drain"           : "F - 2",
        "descriptors"     : [ "physical" ]
      },
      { "unique_id"     : "MANA_BARRIER",
        "translations" : 
        { 
            "en" : "Mana Barrier",
            "de" : "Manabarriere"
        },
        "category"        : "MANIPULATION",
        "type"            : "M",
        "range"           : "LOS(A)",
        "duration"        : "S",
        "drain"           : "F - 2",
        "descriptors"     : [ "environmental", "area" ]
      },
      { "unique_id"     : "PHYSICAL_BARRIER",
        "translations" : 
        { 
            "en" : "Physical Barrier",
            "de" : "Physische Barriere"
        },
        "category"        : "MANIPULATION",
        "type"            : "P",
        "range"           : "LOS(A)",
        "duration"        : "S",
        "drain"           : "F - 1",
        "descriptors"     : [ "environmental", "area" ]
      },
      { "unique_id"     : "POLTERGEIST",
        "translations" : 
        { 
            "en" : "Poltergeist",
            "de" : "Poltergeist"
        },
        "category"        : "MANIPULATION",
        "type"            : "P",
        "range"           : "LOS(A)",
        "duration"        : "S",
        "drain"           : "F - 2",
        "descriptors"     : [ "environmental", "area" ]
      },
      { "unique_id"     : "SHADOW",
        "translations" : 
        { 
            "en" : "Shadow",
            "de" : "Schatten"
        },
        "category"        : "MANIPULATION",
        "type"            : "P",
        "range"           : "LOS(A)",
        "duration"        : "S",
        "drain"           : "F - 3",
        "descriptors"     : [ "environmental", "area" ]
      }
    ],
    "adept_powers" : [
      { "unique_id"    : "ADRENALINE_BOOST",
        "translations" :
        {
            "en"    : "Adrenaline Boost",
            "de"    : "Adrenalinschub"
        },
        "cost_per_level"    : "0.25",
        "activation"        : "free"
      },
      { "unique_id"    : "ASTRAL_PERCEPTION",
        "translations" :
        {
            "en"    : "Astral Perception",
            "de"    : "Astrale Wahrnehmung"
        },
        "cost"              : "1",
        "activation"        : "simple"
      },
      { "unique_id"    : "ATTRIBUTE_BOOST",
        "translations" :
        {
            "en"    : "Attribute Boost",
            "de"    : "Attributsschub"
        },
        "cost_per_level"    : "0.25",
        "requires_custom"   : "true",
        "activation"        : "simple"
      },
      { "unique_id"    : "COMBAT_SENSE_ADEPT",
        "translations" :
        {
            "en"    : "Combat Sense",
            "de"    : "Kampfsinn"
        },
        "cost_per_level"    : "0.5"
      },
      { "unique_id"    : "CRITICAL_STRIKE",
        "translations" :
        {
            "en"    : "Critical Strike",
            "de"    : "Kritischer Schlag"
        },
        "cost"              : "0.25",
        "requires_custom"   : "true"
      },
      { "unique_id"    : "DANGER_SENSE",
        "translations" :
        {
            "en"    : "Danger Sense",
            "de"    : "Gefahrensinn"
        },
        "cost_per_level"    : "0.25"
      },
      { "unique_id"    : "ENHANCED_PERCEPTION",
        "translations" :
        {
            "en"    : "Enhanced Perception",
            "de"    : "Verbesserte Wahrnehmung"
        },
        "cost_per_level"    : "0.5"
      },
      { "unique_id"    : "ENHANCED_ACCURACY",
        "translations" :
        {
            "en"    : "Enhanced Accuracy",
            "de"    : "Erhöhte Präzision"
        },
        "cost"              : "0.25",
        "requires_custom"   : "true"
      },
      { "unique_id"    : "IMPROVED_ABILITY",
        "translations" :
        {
            "en"    : "Improved Ability",
            "de"    : "Verbesserte Fertigkeit"
        },
        "cost_per_level"    : "0.5",
        "requires_custom"   : "true",
        "custom_choices"    : {
            "type"             : "skill_selection",
            "groups_allowed"   : "false",
            "categories"       : ["combat", "social", "physical", "vehicle"]
        },
        "effects" : [
            {
                "type"         : "increase_skill",
                "skill"        : "selected",
                "value"        : "1",
                "limit"        : "1.5 * pure_skill_value",
                "conditions" : [ "skill_known" ]
            }
        ]
      },
      { "unique_id"    : "IMPROVED_PHYS_ATTRIBUTE",
        "translations" :
        {
            "en"    : "Improved Physical Attribute",
            "de"    : "Gesteigertes Körperliches Attribut"
        },
        "cost_per_level"    : "1",
        "requires_custom"   : "true",
        "custom_choices"    : {
            "type"             : "attribute_selection",
            "attributes"       : ["body", "agility", "reaction", "strength"]
        },
        "effects" : [
            {
                "type"         : "increase_attribute",
                "attribute"    : "selected",
                "value"        : "1",
                "limit"        : "1.0 * augmented_maximum"
            }
        ]
      },
      { "unique_id"    : "IMPROVED_POTENTIAL",
        "translations" :
        {
            "en"    : "Improved Potential",
            "de"    : "Erhöhtes Potenzial"
        },
        "cost_per_level"    : "0.5",
        "requires_custom"   : "true"
      },
      { "unique_id"    : "IMPROVED_REFLEXES",
        "translations" :
        {
            "en"    : "Improved Reflexes",
            "de"    : "Gesteigerte Reflexe"
        },
        "cost"    : [ "1.5", "2.5", "3.5" ]
      },
      { "unique_id"    : "IMPROVED_SENSE_DIRECTION",
        "translations" :
        {
            "en"    : "Improved Sense",
            "de"    : "Geschärfter Sinn"
        },
        "cost"              : "0.25",
        "requires_custom"   : "true"
      },
      { "unique_id"    : "KILLING_HANDS",
        "translations" :
        {
            "en"    : "Killing Hands",
            "de"    : "Todeskralle"
        },
        "cost"              : "0.5",
        "activation"        : "free"
      },
      { "unique_id"    : "KINESICS",
        "translations" :
        {
            "en"    : "Kinesics",
            "de"    : "Körpersprache"
        },
        "cost_per_level"    : "0.25"
      },
      { "unique_id"    : "LIGHT_BODY",
        "translations" :
        {
            "en"    : "Light Body",
            "de"    : "Leichter Körper"
        },
        "cost_per_level"    : "0.25"
      },
      { "unique_id"    : "MISSILE_PARRY",
        "translations" :
        {
            "en"    : "Missile Parry",
            "de"    : "Geschossparade"
        },
        "cost_per_level"    : "0.25",
        "activation"        : "interrupt"
      },
      { "unique_id"    : "MYSTIC_ARMOR",
        "translations" :
        {
            "en"    : "Mystic Armor",
            "de"    : "Mytischer Panzer"
        },
        "cost_per_level"    : "0.5"
      },
      { "unique_id"    : "NATURAL_IMMUNITY",
        "translations" :
        {
            "en"    : "Natural Immunity",
            "de"    : "Natürliche Immunität"
        },
        "cost_per_level"    : "0.25"
      },
      { "unique_id"    : "PAIN_RESISTANCE",
        "translations" :
        {
            "en"    : "Pain Resistance",
            "de"    : "Schmerzresistenz"
        },
        "cost_per_level"    : "0.5"
      },
      { "unique_id"    : "RAPID_HEALING",
        "translations" :
        {
            "en"    : "Rapid Healing",
            "de"    : "Beschleunigte heilung"
        },
        "cost_per_level"    : "0.5"
      },
      { "unique_id"    : "SPELL_RESISTANCE",
        "translations" :
        {
            "en"    : "Spell Resistance",
            "de"    : "Magieresistenz"
        },
        "cost_per_level"    : "0.5"
      },
      { "unique_id"    : "TRACELESS_WALK",
        "translations" :
        {
            "en"    : "Traceless Walk",
            "de"    : "Spurloser Schritt"
        },
        "cost"         : "1"
      },
      { "unique_id"    : "VOICE_CONTROL",
        "translations" :
        {
            "en"    : "Voice Control",
            "de"    : "Stimmkontrolle"
        },
        "cost_per_level"    : "0.5"
      },
      { "unique_id"    : "WALL_RUNNING",
        "translations" :
        {
            "en"    : "Wall Running",
            "de"    : "Wandlaufen"
        },
        "cost"          : "0.5",
        "activation"    : "simple"
      }
    ],
    "complex_forms" : [
      { "unique_id"    : "CLEANER",
        "translations" :
        {
            "en"    : "Cleaner",
            "de"    : "Reiniger"
        },
        "target"          : "persona",
        "duration"        : "P",   
        "fading_value"    : "L + 1"
      },
      { "unique_id"    : "DIFFUSION_OF_MA",
        "translations" :
        {
            "en"    : "Diffusion Of [Matrix Attribute]",
            "de"    : "[Matrixattribut]-Senkung"
        },
        "target"          : "device",
        "duration"        : "S",
        "requires_custom" : "true",
        "fading_value"    : "L + 1"
      },
      { "unique_id"    : "EDITOR",
        "translations" :
        {
            "en"    : "Editor",
            "de"    : "Editor"
        },
        "target"          : "file",
        "duration"        : "P",   
        "fading_value"    : "L + 2"
      },
      { "unique_id"    : "INFUSION_OF_MA",
        "translations" :
        {
            "en"    : "Infusion Of [Matrix Attribute]",
            "de"    : "[Matrixattribut]-Steigerung"
        },
        "target"          : "device",
        "duration"        : "S",   
        "requires_custom" : "true",
        "fading_value"    : "L + 1"
      },
      { "unique_id"    : "STATIC_VEIL",
        "translations" :
        {
            "en"    : "Static Veil",
            "de"    : "Signalschleier"
        },
        "target"          : "persona",
        "duration"        : "S",   
        "fading_value"    : "L - 1"
      },
      { "unique_id"    : "PULSE_STORM",
        "translations" :
        {
            "en"    : "Pulse Storm",
            "de"    : "Signalsturm"
        },
        "target"          : "persona",
        "duration"        : "I",   
        "fading_value"    : "L"
      },
      { "unique_id"    : "PUPPETEER",
        "translations" :
        {
            "en"    : "Puppeteer",
            "de"    : "Puppenspieler"
        },
        "target"          : "device",
        "duration"        : "I",   
        "fading_value"    : "L + 4"
      },
      { "unique_id"    : "RESONANCE_CHANNEL",
        "translations" :
        {
            "en"    : "Resonance Channel",
            "de"    : "Resonanzkanal"
        },
        "target"          : "device",
        "duration"        : "S",   
        "fading_value"    : "L - 1"
      },
      { "unique_id"    : "RESONANCE_SPIKE",
        "translations" :
        {
            "en"    : "Resonance Spike",
            "de"    : "Resonanzspitze"
        },
        "target"          : "device",
        "duration"        : "I",   
        "fading_value"    : "L"
      },
      { "unique_id"    : "RESONANCE_VEIL",
        "translations" :
        {
            "en"    : "Resonance Veil",
            "de"    : "Resonanzillusion"
        },
        "target"          : "device",
        "duration"        : "S",   
        "fading_value"    : "L - 1"
      },
      { "unique_id"    : "STATIC_BOMB",
        "translations" :
        {
            "en"    : "Static Bomb",
            "de"    : "Resonanznebel"
        },
        "target"          : "persona",
        "duration"        : "I",   
        "fading_value"    : "L + 2"
      },
      { "unique_id"    : "STITCHES",
        "translations" :
        {
            "en"    : "Stitches",
            "de"    : "Zusammenflicken"
        },
        "target"          : "sprite",
        "duration"        : "P",   
        "fading_value"    : "L - 2"
      },
      { "unique_id"    : "TRANSCENDENT_GRID",
        "translations" :
        {
            "en"    : "Transcendent Grid",
            "de"    : "Metagitter"
        },
        "target"          : "persona",
        "duration"        : "I",   
        "fading_value"    : "L - 3"
      },
      { "unique_id"    : "TELLTALE",
        "translations" :
        {
            "en"    : "Telltale",
            "de"    : "Petze"
        },
        "target"          : "persona",
        "duration"        : "P",   
        "fading_value"    : "L - 2"
      }
    ]
}